deepl/__init__.py
deepl/deepl.py
deepl/languages.py
deepl/main.py
deepl/py.typed
deepl_cli-2.2.0.dist-info/METADATA
deepl_cli-2.2.0.dist-info/WHEEL
deepl_cli-2.2.0.dist-info/entry_points.txt
deepl_cli-2.2.0.dist-info/licenses/LICENSE
deepl_cli-2.2.0.dist-info/RECORD
