Metadata-Version: 2.4
Name: deepl-cli
Version: 2.2.0
Summary: DeepL Translator CLI without API Key
Project-URL: Repository, https://github.com/eggplants/deepl-cli
Author-email: eggplants <w10776e8w@yahoo.co.jp>
License: MIT
License-File: LICENSE
Keywords: cli,deepl,translate
Classifier: License :: OSI Approved :: MIT License
Classifier: Programming Language :: Python :: 3 :: Only
Classifier: Programming Language :: Python :: 3.10
Classifier: Programming Language :: Python :: 3.11
Classifier: Programming Language :: Python :: 3.12
Classifier: Programming Language :: Python :: 3.13
Classifier: Programming Language :: Python :: 3.14
Classifier: Topic :: Text Processing :: Linguistic
Classifier: Typing :: Typed
Requires-Python: <4,>=3.10
Requires-Dist: install-playwright<0.2,>=0.1
Requires-Dist: playwright<2,>=1.49.1
